barx-0.1.0.dist-info/METADATA
barx-0.1.0.dist-info/WHEEL
barx-0.1.0.dist-info/entry_points.txt
barx/cli.py
barx/data.py
barx/ir/optimizer.py
barx/ir/parser.py
barx/ir/__init__.py
barx/llm.py
barx/nn.py
barx/optim.py
barx/tensor.py
barx/utils.py
barx/__init__.py
barx/_rust_kernels.pyd
barx-0.1.0.dist-info/RECORD
