Metadata-Version: 2.4
Name: barx
Version: 0.1.0
Classifier: Development Status :: 3 - Alpha
Classifier: Intended Audience :: Developers
Classifier: Intended Audience :: Science/Research
Classifier: License :: OSI Approved :: MIT License
Classifier: Operating System :: OS Independent
Classifier: Programming Language :: Python :: 3
Classifier: Programming Language :: Python :: 3.8
Classifier: Programming Language :: Python :: 3.9
Classifier: Programming Language :: Python :: 3.10
Classifier: Programming Language :: Python :: Implementation :: CPython
Classifier: Topic :: Scientific/Engineering :: Artificial Intelligence
Requires-Dist: numpy>=1.20.0
Requires-Dist: pytest>=7.0.0 ; extra == 'dev'
Requires-Dist: pytest-benchmark>=4.0.0 ; extra == 'dev'
Requires-Dist: black>=22.1.0 ; extra == 'dev'
Requires-Dist: isort>=5.10.1 ; extra == 'dev'
Requires-Dist: pytest>=7.0.0 ; extra == 'test'
Requires-Dist: pytest-benchmark>=4.0.0 ; extra == 'test'
Provides-Extra: dev
Provides-Extra: test
Summary: Fast, CPU-only AI framework for Python developers
Author: BARX Team
Author-email: BARX Team <aura@barx.ai>
License: MIT
Requires-Python: >=3.8
Project-URL: Homepage, https://github.com/barx-team/barx
Project-URL: Documentation, https://barx.readthedocs.io
Project-URL: Repository, https://github.com/barx-team/barx
Project-URL: Issues, https://github.com/barx-team/barx/issues
